{"title":"BLK-173 Aoiyama Miina JAV CENSORED","uid":10875715,"size":1818346944,"categoryP":"porn","categoryS":"movie_clips","magnet":"?xt=urn:btih:0a5497655c3639a9cb627c747b4d60a07f1778d4&amp;dn=BLK-173+Aoiyama+Miina+JAV+CENSORED&amp;tr=udp%3A%2F%2Ftracker.openbittorrent.com%3A80&amp;tr=udp%3A%2F%2Fopen.demonii.com%3A1337&amp;tr=udp%3A%2F%2Ftracker.coppersurfer.tk%3A6969&amp;tr=udp%3A%2F%2Fexodus.desync.com%3A6969","seeders":0,"leechers":1,"uploader":"3xplanet","files":1,"time":1408989555,"description":"BLK-173 Aoiyama Miina JAV CENSORED\nCover &lt;a href=&quot;\nhttp://www.3xplanet.com/view/53211.html&quot; rel=&quot;nofollow&quot; target=&quot;_NEW&quot;&gt;\nhttp://www.3xplanet.com/view/53211.html&lt;/a&gt;\nScreenshot &lt;a href=&quot;\nhttp://www.3xplanet.com/view/53290.html&quot; rel=&quot;nofollow&quot; target=&quot;_NEW&quot;&gt;\nhttp://www.3xplanet.com/view/53290.html&lt;/a&gt;\nTitle: \nStarring: Aoiyama Miina\nStudio:  kira â˜† kira\n\nTag: JAV, CENSORED, kira â˜† kira, Work alone, vibe, gal, debut, debut, cum inside, Creampie, cowgirl\n\n","torrent":{"xt":"urn:btih:0a5497655c3639a9cb627c747b4d60a07f1778d4","amp;dn":"BLK-173+Aoiyama+Miina+JAV+CENSORED","amp;tr":["udp%3A%2F%2Ftracker.openbittorrent.com%3A80","udp%3A%2F%2Fopen.demonii.com%3A1337","udp%3A%2F%2Ftracker.coppersurfer.tk%3A6969","udp%3A%2F%2Fexodus.desync.com%3A6969"],"infoHash":"0a5497655c3639a9cb627c747b4d60a07f1778d4","infoHashBuffer":{"type":"Buffer","data":[10,84,151,101,92,54,57,169,203,98,124,116,123,77,96,160,127,23,120,212]},"announce":[],"urlList":[]}}