{"title":"FuckedHard18 - Sensi Pearl","uid":11803067,"size":617416231,"categoryP":"porn","categoryS":"other","magnet":"?xt=urn:btih:0b1be2b253ca18cb38ec218b842c14780c05a9c4&amp;dn=FuckedHard18+-+Sensi+Pearl&amp;tr=udp%3A%2F%2Ftracker.openbittorrent.com%3A80&amp;tr=udp%3A%2F%2Fopen.demonii.com%3A1337&amp;tr=udp%3A%2F%2Ftracker.coppersurfer.tk%3A6969&amp;tr=udp%3A%2F%2Fexodus.desync.com%3A6969","seeders":0,"leechers":1,"uploader":"bittuboss","files":1,"time":1428485260,"description":"ScReenS...\n\n &lt;a href=&quot;\nhttp://imgextra.biz/img-5524d827585ad.html&quot; rel=&quot;nofollow&quot; target=&quot;_NEW&quot;&gt;\nhttp://imgextra.biz/img-5524d827585ad.html&lt;/a&gt;\n &lt;a href=&quot;\nhttp://imgextra.biz/img-5524d82909999.html&quot; rel=&quot;nofollow&quot; target=&quot;_NEW&quot;&gt;\nhttp://imgextra.biz/img-5524d82909999.html&lt;/a&gt;","torrent":{"xt":"urn:btih:0b1be2b253ca18cb38ec218b842c14780c05a9c4","amp;dn":"FuckedHard18+-+Sensi+Pearl","amp;tr":["udp%3A%2F%2Ftracker.openbittorrent.com%3A80","udp%3A%2F%2Fopen.demonii.com%3A1337","udp%3A%2F%2Ftracker.coppersurfer.tk%3A6969","udp%3A%2F%2Fexodus.desync.com%3A6969"],"infoHash":"0b1be2b253ca18cb38ec218b842c14780c05a9c4","infoHashBuffer":{"type":"Buffer","data":[11,27,226,178,83,202,24,203,56,236,33,139,132,44,20,120,12,5,169,196]},"announce":[],"urlList":[]}}