{"title":"Hollyoaks.2015.02.09.mp4","uid":11763912,"size":144442076,"categoryP":"video","categoryS":"movie_clips","magnet":"?xt=urn:btih:0f2a4f097a4253709f8a5b48509598e9c8bd7dde&amp;dn=Hollyoaks.2015.02.09.mp4&amp;tr=udp%3A%2F%2Ftracker.openbittorrent.com%3A80&amp;tr=udp%3A%2F%2Fopen.demonii.com%3A1337&amp;tr=udp%3A%2F%2Ftracker.coppersurfer.tk%3A6969&amp;tr=udp%3A%2F%2Fexodus.desync.com%3A6969","seeders":0,"leechers":1,"uploader":"mickedee77","files":1,"time":1426668668,"description":"Hollyoaks 9th February 2015","torrent":{"xt":"urn:btih:0f2a4f097a4253709f8a5b48509598e9c8bd7dde","amp;dn":"Hollyoaks.2015.02.09.mp4","amp;tr":["udp%3A%2F%2Ftracker.openbittorrent.com%3A80","udp%3A%2F%2Fopen.demonii.com%3A1337","udp%3A%2F%2Ftracker.coppersurfer.tk%3A6969","udp%3A%2F%2Fexodus.desync.com%3A6969"],"infoHash":"0f2a4f097a4253709f8a5b48509598e9c8bd7dde","infoHashBuffer":{"type":"Buffer","data":[15,42,79,9,122,66,83,112,159,138,91,72,80,149,152,233,200,189,125,222]},"announce":[],"urlList":[]}}