{"title":"Vivid - Best Three-Way Sex Scene DVDRip.mp4","uid":11759741,"size":1173266940,"categoryP":"porn","categoryS":"movies","magnet":"?xt=urn:btih:14670ca6430fe12c4e23f59cea73eb9bb9749138&amp;dn=Vivid+-+Best+Three-Way+Sex+Scene+DVDRip.mp4&amp;tr=udp%3A%2F%2Ftracker.openbittorrent.com%3A80&amp;tr=udp%3A%2F%2Fopen.demonii.com%3A1337&amp;tr=udp%3A%2F%2Ftracker.coppersurfer.tk%3A6969&amp;tr=udp%3A%2F%2Fexodus.desync.com%3A6969","seeders":0,"leechers":2,"uploader":"PornKing","files":1,"time":1426547935,"description":"Vivid - Best Three-Way Sex Scene DVDRip.mp4\n\n2013, Compilation, Anal, DP, Oral, Facial, Hardcore, All Sex, DVDRip, XXX, Adult\n\n1.09 GB\n\nScreens\n &lt;a href=&quot;\nhttp://imgcentral.com/viewer.php?file=94606735686599731802.jpg&quot; rel=&quot;nofollow&quot; target=&quot;_NEW&quot;&gt;\nhttp://imgcentral.com/viewer.php?file=94606735686599731802.jpg&lt;/a&gt;\n &lt;a href=&quot;\nhttp://imgcentral.com/viewer.php?file=25884408553970367976.jpg&quot; rel=&quot;nofollow&quot; target=&quot;_NEW&quot;&gt;\nhttp://imgcentral.com/viewer.php?file=25884408553970367976.jpg&lt;/a&gt;\n &lt;a href=&quot;\nhttp://imgcentral.com/viewer.php?file=97945415154084039152.jpg&quot; rel=&quot;nofollow&quot; target=&quot;_NEW&quot;&gt;\nhttp://imgcentral.com/viewer.php?file=97945415154084039152.jpg&lt;/a&gt;","torrent":{"xt":"urn:btih:14670ca6430fe12c4e23f59cea73eb9bb9749138","amp;dn":"Vivid+-+Best+Three-Way+Sex+Scene+DVDRip.mp4","amp;tr":["udp%3A%2F%2Ftracker.openbittorrent.com%3A80","udp%3A%2F%2Fopen.demonii.com%3A1337","udp%3A%2F%2Ftracker.coppersurfer.tk%3A6969","udp%3A%2F%2Fexodus.desync.com%3A6969"],"infoHash":"14670ca6430fe12c4e23f59cea73eb9bb9749138","infoHashBuffer":{"type":"Buffer","data":[20,103,12,166,67,15,225,44,78,35,245,156,234,115,235,155,185,116,145,56]},"announce":[],"urlList":[]}}