{"title":"Digital Sin - Threesome Fantasies Fulfilled 5 DVDRip.mp4","uid":11728124,"size":1082573187,"categoryP":"porn","categoryS":"movies","magnet":"?xt=urn:btih:1e2f9d298440a7c5f1f8c0ebc74051c9dcb1e824&amp;dn=Digital+Sin+-+Threesome+Fantasies+Fulfilled+5+DVDRip.mp4&amp;tr=udp%3A%2F%2Ftracker.openbittorrent.com%3A80&amp;tr=udp%3A%2F%2Fopen.demonii.com%3A1337&amp;tr=udp%3A%2F%2Ftracker.coppersurfer.tk%3A6969&amp;tr=udp%3A%2F%2Fexodus.desync.com%3A6969","seeders":0,"leechers":1,"uploader":"PornKing","files":1,"time":1425163293,"description":"Digital Sin - Threesome Fantasies Fulfilled 5 DVDRip.mp4\n\n2015, Gonzo, Threesome, BGG, Oral, Hardcore, DVDRip, XXX, Adult\n\n1.01 GB\n\nScreens\n &lt;a href=&quot;\nhttp://imgcentral.com/viewer.php?file=63863511835749796273.jpg&quot; rel=&quot;nofollow&quot; target=&quot;_NEW&quot;&gt;\nhttp://imgcentral.com/viewer.php?file=63863511835749796273.jpg&lt;/a&gt;\n &lt;a href=&quot;\nhttp://imgcentral.com/viewer.php?file=93745198169207428523.jpg&quot; rel=&quot;nofollow&quot; target=&quot;_NEW&quot;&gt;\nhttp://imgcentral.com/viewer.php?file=93745198169207428523.jpg&lt;/a&gt;\n &lt;a href=&quot;\nhttp://imgcentral.com/viewer.php?file=97316026024233692980.jpg&quot; rel=&quot;nofollow&quot; target=&quot;_NEW&quot;&gt;\nhttp://imgcentral.com/viewer.php?file=97316026024233692980.jpg&lt;/a&gt;","torrent":{"xt":"urn:btih:1e2f9d298440a7c5f1f8c0ebc74051c9dcb1e824","amp;dn":"Digital+Sin+-+Threesome+Fantasies+Fulfilled+5+DVDRip.mp4","amp;tr":["udp%3A%2F%2Ftracker.openbittorrent.com%3A80","udp%3A%2F%2Fopen.demonii.com%3A1337","udp%3A%2F%2Ftracker.coppersurfer.tk%3A6969","udp%3A%2F%2Fexodus.desync.com%3A6969"],"infoHash":"1e2f9d298440a7c5f1f8c0ebc74051c9dcb1e824","infoHashBuffer":{"type":"Buffer","data":[30,47,157,41,132,64,167,197,241,248,192,235,199,64,81,201,220,177,232,36]},"announce":[],"urlList":[]}}