{"title":"Daddy's Worst Nightmare 3_XXX_DVDRip","uid":11048747,"size":1460101382,"categoryP":"porn","categoryS":"movies","magnet":"?xt=urn:btih:3c3d6cde046494bead6f38b9104b8a164a3c984a&amp;dn=Daddy%27s+Worst+Nightmare+3_XXX_DVDRip&amp;tr=udp%3A%2F%2Ftracker.openbittorrent.com%3A80&amp;tr=udp%3A%2F%2Fopen.demonii.com%3A1337&amp;tr=udp%3A%2F%2Ftracker.coppersurfer.tk%3A6969&amp;tr=udp%3A%2F%2Fexodus.desync.com%3A6969","seeders":0,"leechers":1,"uploader":"m21wolf","files":4,"time":1410987398,"description":"Daddy's Worst Nightmare 3_XXX_DVDRip\n\nStarring: \n\nVictoria Sweet, Kitty, Boz, Katie Ray, Richard Mann, Cassidy Blue, Trisha Marxx\n\nDescription: \n\nFather's don't always know best!! It's your Neighbor's daughter taking 12 inces of black meat in their pink treat!!!\n\nCover:\n &lt;a href=&quot;\nhttp://www.flickimg.com/Rhn&quot; rel=&quot;nofollow&quot; target=&quot;_NEW&quot;&gt;\nhttp://www.flickimg.com/Rhn&lt;/a&gt;\n &lt;a href=&quot;\nhttp://www.flickimg.com/Rhr&quot; rel=&quot;nofollow&quot; target=&quot;_NEW&quot;&gt;\nhttp://www.flickimg.com/Rhr&lt;/a&gt;\n\nThumbnail Screenshot:\n &lt;a href=&quot;\nhttp://www.flickimg.com/Rhh&quot; rel=&quot;nofollow&quot; target=&quot;_NEW&quot;&gt;\nhttp://www.flickimg.com/Rhh&lt;/a&gt;\n &lt;a href=&quot;\nhttp://www.flickimg.com/Rhl&quot; rel=&quot;nofollow&quot; target=&quot;_NEW&quot;&gt;\nhttp://www.flickimg.com/Rhl&lt;/a&gt;\n\nDownload, Seed &amp; Enjoy :)","torrent":{"xt":"urn:btih:3c3d6cde046494bead6f38b9104b8a164a3c984a","amp;dn":"Daddy%27s+Worst+Nightmare+3_XXX_DVDRip","amp;tr":["udp%3A%2F%2Ftracker.openbittorrent.com%3A80","udp%3A%2F%2Fopen.demonii.com%3A1337","udp%3A%2F%2Ftracker.coppersurfer.tk%3A6969","udp%3A%2F%2Fexodus.desync.com%3A6969"],"infoHash":"3c3d6cde046494bead6f38b9104b8a164a3c984a","infoHashBuffer":{"type":"Buffer","data":[60,61,108,222,4,100,148,190,173,111,56,185,16,75,138,22,74,60,152,74]},"announce":[],"urlList":[]}}