{"title":"MassageRooms.Fernando.And.Coco.XXX.1080p.BTY.mp4","uid":11739453,"size":1098226551,"categoryP":"porn","categoryS":"movies","magnet":"?xt=urn:btih:3cab86d7a4692eaa900e9548705c40a3ba4fc020&amp;dn=MassageRooms.Fernando.And.Coco.XXX.1080p.BTY.mp4&amp;tr=udp%3A%2F%2Ftracker.openbittorrent.com%3A80&amp;tr=udp%3A%2F%2Fopen.demonii.com%3A1337&amp;tr=udp%3A%2F%2Ftracker.coppersurfer.tk%3A6969&amp;tr=udp%3A%2F%2Fexodus.desync.com%3A6969","seeders":0,"leechers":1,"uploader":"jepsrmnt","files":1,"time":1425715740,"description":"MassageRooms.Fernando.And.Coco.XXX.1080p.BTY\n\npreview &lt;a href=&quot;\nhttp://booooty.com/?v=MassageRooms.Fernando.And.Coco.XXX.1080p.BTY_s.jpg&quot; rel=&quot;nofollow&quot; target=&quot;_NEW&quot;&gt;\nhttp://booooty.com/?v=MassageRooms.Fernando.And.Coco.XXX.1080p.BTY_s.jpg&lt;/a&gt;","torrent":{"xt":"urn:btih:3cab86d7a4692eaa900e9548705c40a3ba4fc020","amp;dn":"MassageRooms.Fernando.And.Coco.XXX.1080p.BTY.mp4","amp;tr":["udp%3A%2F%2Ftracker.openbittorrent.com%3A80","udp%3A%2F%2Fopen.demonii.com%3A1337","udp%3A%2F%2Ftracker.coppersurfer.tk%3A6969","udp%3A%2F%2Fexodus.desync.com%3A6969"],"infoHash":"3cab86d7a4692eaa900e9548705c40a3ba4fc020","infoHashBuffer":{"type":"Buffer","data":[60,171,134,215,164,105,46,170,144,14,149,72,112,92,64,163,186,79,192,32]},"announce":[],"urlList":[]}}