{"title":"MomXXX - Feel Her - Morgan Blanchet [720p].mov","uid":11723639,"size":947737207,"categoryP":"porn","categoryS":"hd___movies","magnet":"?xt=urn:btih:4e1a1a7f22a6003d68f58f99de3198cc8d5291e1&amp;dn=MomXXX+-+Feel+Her+-+Morgan+Blanchet+%5B720p%5D.mov&amp;tr=udp%3A%2F%2Ftracker.openbittorrent.com%3A80&amp;tr=udp%3A%2F%2Fopen.demonii.com%3A1337&amp;tr=udp%3A%2F%2Ftracker.coppersurfer.tk%3A6969&amp;tr=udp%3A%2F%2Fexodus.desync.com%3A6969","seeders":0,"leechers":1,"uploader":"1.No.1","files":1,"time":1424967813,"description":"MomXXX - Feel Her - Morgan Blanchet [720p].mov\n\n2015, All Sex, Oral, MILF, Mature, Gonzo, Hardcore, HD, XXX, Adult\n\n903.83 MB\n\nScreens\n &lt;a href=&quot;\nhttp://pixsor.com/share-F5C0_54EF3A36.html&quot; rel=&quot;nofollow&quot; target=&quot;_NEW&quot;&gt;\nhttp://pixsor.com/share-F5C0_54EF3A36.html&lt;/a&gt;\n &lt;a href=&quot;\nhttp://pixsor.com/share-BFF3_54EF3A37.html&quot; rel=&quot;nofollow&quot; target=&quot;_NEW&quot;&gt;\nhttp://pixsor.com/share-BFF3_54EF3A37.html&lt;/a&gt;\n &lt;a href=&quot;\nhttp://pixsor.com/share-A46F_54EF3A38.html&quot; rel=&quot;nofollow&quot; target=&quot;_NEW&quot;&gt;\nhttp://pixsor.com/share-A46F_54EF3A38.html&lt;/a&gt;\n &lt;a href=&quot;\nhttp://pixsor.com/share-0DB2_54EF3A39.html&quot; rel=&quot;nofollow&quot; target=&quot;_NEW&quot;&gt;\nhttp://pixsor.com/share-0DB2_54EF3A39.html&lt;/a&gt;","torrent":{"xt":"urn:btih:4e1a1a7f22a6003d68f58f99de3198cc8d5291e1","amp;dn":"MomXXX+-+Feel+Her+-+Morgan+Blanchet+%5B720p%5D.mov","amp;tr":["udp%3A%2F%2Ftracker.openbittorrent.com%3A80","udp%3A%2F%2Fopen.demonii.com%3A1337","udp%3A%2F%2Ftracker.coppersurfer.tk%3A6969","udp%3A%2F%2Fexodus.desync.com%3A6969"],"infoHash":"4e1a1a7f22a6003d68f58f99de3198cc8d5291e1","infoHashBuffer":{"type":"Buffer","data":[78,26,26,127,34,166,0,61,104,245,143,153,222,49,152,204,141,82,145,225]},"announce":[],"urlList":[]}}