{"title":"SuicideGirls.14.08.08.River.Lost.Creek.XXX.iMAGESET-OHRLY","uid":10736398,"size":40947902,"categoryP":"porn","categoryS":"other","magnet":"?xt=urn:btih:57688818953d82e940cbbb0335c5d42b16a7acad&amp;dn=SuicideGirls.14.08.08.River.Lost.Creek.XXX.iMAGESET-OHRLY&amp;tr=udp%3A%2F%2Ftracker.openbittorrent.com%3A80&amp;tr=udp%3A%2F%2Fopen.demonii.com%3A1337&amp;tr=udp%3A%2F%2Ftracker.coppersurfer.tk%3A6969&amp;tr=udp%3A%2F%2Fexodus.desync.com%3A6969","seeders":0,"leechers":1,"uploader":"DrarbgXXX","files":48,"time":1407696527,"description":" &lt;a href=&quot;https://rarbg.com&quot; rel=&quot;nofollow&quot; target=&quot;_NEW&quot;&gt;https://rarbg.com&lt;/a&gt;\n\nSuicideGirls.com_14.08.08.River.Lost.Creek.XXX.iMAGESET-OHRLY\n","torrent":{"xt":"urn:btih:57688818953d82e940cbbb0335c5d42b16a7acad","amp;dn":"SuicideGirls.14.08.08.River.Lost.Creek.XXX.iMAGESET-OHRLY","amp;tr":["udp%3A%2F%2Ftracker.openbittorrent.com%3A80","udp%3A%2F%2Fopen.demonii.com%3A1337","udp%3A%2F%2Ftracker.coppersurfer.tk%3A6969","udp%3A%2F%2Fexodus.desync.com%3A6969"],"infoHash":"57688818953d82e940cbbb0335c5d42b16a7acad","infoHashBuffer":{"type":"Buffer","data":[87,104,136,24,149,61,130,233,64,203,187,3,53,197,212,43,22,167,172,173]},"announce":[],"urlList":[]}}