{"title":"Stuck.on.You.2003.MULTiSUBS.PAL.DVDR-DiSHON","uid":11794532,"size":4696475648,"categoryP":"video","categoryS":"movies_dvdr","magnet":"?xt=urn:btih:60260c4052ea776abfdb1819a79ac2408bb05e2d&amp;dn=Stuck.on.You.2003.MULTiSUBS.PAL.DVDR-DiSHON&amp;tr=udp%3A%2F%2Ftracker.openbittorrent.com%3A80&amp;tr=udp%3A%2F%2Fopen.demonii.com%3A1337&amp;tr=udp%3A%2F%2Ftracker.coppersurfer.tk%3A6969&amp;tr=udp%3A%2F%2Fexodus.desync.com%3A6969","seeders":0,"leechers":1,"uploader":"dishon","files":10,"time":1428078323,"description":"Stuck on You (2003)  \n\nName.....Stuck.on.You.2003.MULTiSUBS.PAL.DVDR-DiSHON\n\nSource............Blu-Ray + DVD\nSize..............4,37 GB  \n\nDVD INFO:\n\nAspect Ratio.....Widescreen 16:9\nStandard.........PAL\nAudio............English Dolby 5.1\nSubtitles........English, Bulgarian, Croatian, Romanian,\n.................Russian, Slovenian, Turkish, Dansk\nVideo............Converted from Blu-Ray, bitrate = 4883 Kbs\nMenu.............Edit\nExtras...........No \nRegion...........Free\n\nGenre............Comedy                 \nIMDB Rating......5,8/10 from 41.114 users\nRuntime..........118 min\nCountry..........USA\nYear.............2003\nInfo Link........http://www.imdb.com/title/tt0338466/\n\nPlot:\n\nConjoined twins from Martha's Vineyard move to Los Angeles so that \none of them can pursue an acting career","torrent":{"xt":"urn:btih:60260c4052ea776abfdb1819a79ac2408bb05e2d","amp;dn":"Stuck.on.You.2003.MULTiSUBS.PAL.DVDR-DiSHON","amp;tr":["udp%3A%2F%2Ftracker.openbittorrent.com%3A80","udp%3A%2F%2Fopen.demonii.com%3A1337","udp%3A%2F%2Ftracker.coppersurfer.tk%3A6969","udp%3A%2F%2Fexodus.desync.com%3A6969"],"infoHash":"60260c4052ea776abfdb1819a79ac2408bb05e2d","infoHashBuffer":{"type":"Buffer","data":[96,38,12,64,82,234,119,106,191,219,24,25,167,154,194,64,139,176,94,45]},"announce":[],"urlList":[]}}