{"title":"Finding.Carter.S01E12.One.Hour.Photo.1080p.WEB-DL.AAC2.0.h264-QU","uid":11050162,"size":1513136264,"categoryP":"video","categoryS":"hd___tv_shows","magnet":"?xt=urn:btih:73f11e3ff9c1d9fc153ae282e7bfa2684b74f01f&amp;dn=Finding.Carter.S01E12.One.Hour.Photo.1080p.WEB-DL.AAC2.0.h264-QU&amp;tr=udp%3A%2F%2Ftracker.openbittorrent.com%3A80&amp;tr=udp%3A%2F%2Fopen.demonii.com%3A1337&amp;tr=udp%3A%2F%2Ftracker.coppersurfer.tk%3A6969&amp;tr=udp%3A%2F%2Fexodus.desync.com%3A6969","seeders":0,"leechers":1,"uploader":"Drarbg","files":3,"time":1411011301,"description":" &lt;a href=&quot;https://rarbg.com&quot; rel=&quot;nofollow&quot; target=&quot;_NEW&quot;&gt;https://rarbg.com&lt;/a&gt;\n\nFinding.Carter.S01E12.One.Hour.Photo.1080p.WEB-DL.AAC2.0.h264-QUEENS[rartv]\n-----------------------------------------\nScreens : &lt;a href=&quot;\nhttp://imagecurl.org/viewer.php?file=35594233235566807864.jpg&quot; rel=&quot;nofollow&quot; target=&quot;_NEW&quot;&gt;\nhttp://imagecurl.org/viewer.php?file=35594233235566807864.jpg&lt;/a&gt;\n\n-----------------------------------------\nAuto Media Info :\nVideo Format........: AVC\nCodec ID............: V_MPEG4/ISO/AVC\nLength..............: 38mn15s\nVideo...............: 1912x1072 ( 23.976fps )\nAudio Format........: AAC\nCodec ID............: A_AAC\nChannel(s)..........: 2 channels\nEmbeded Subs........: English\n\n","torrent":{"xt":"urn:btih:73f11e3ff9c1d9fc153ae282e7bfa2684b74f01f","amp;dn":"Finding.Carter.S01E12.One.Hour.Photo.1080p.WEB-DL.AAC2.0.h264-QU","amp;tr":["udp%3A%2F%2Ftracker.openbittorrent.com%3A80","udp%3A%2F%2Fopen.demonii.com%3A1337","udp%3A%2F%2Ftracker.coppersurfer.tk%3A6969","udp%3A%2F%2Fexodus.desync.com%3A6969"],"infoHash":"73f11e3ff9c1d9fc153ae282e7bfa2684b74f01f","infoHashBuffer":{"type":"Buffer","data":[115,241,30,63,249,193,217,252,21,58,226,130,231,191,162,104,75,116,240,31]},"announce":[],"urlList":[]}}