{"title":"DoghouseDigital.12.11.29.Her.First.MILF.5.Scene.5.XXX.IMAGESET-G","uid":11049624,"size":182545919,"categoryP":"porn","categoryS":"other","magnet":"?xt=urn:btih:84189aedc04a454965bb6c1ec8242d14cf559039&amp;dn=DoghouseDigital.12.11.29.Her.First.MILF.5.Scene.5.XXX.IMAGESET-G&amp;tr=udp%3A%2F%2Ftracker.openbittorrent.com%3A80&amp;tr=udp%3A%2F%2Fopen.demonii.com%3A1337&amp;tr=udp%3A%2F%2Ftracker.coppersurfer.tk%3A6969&amp;tr=udp%3A%2F%2Fexodus.desync.com%3A6969","seeders":0,"leechers":0,"uploader":"DrarbgXXX","files":180,"time":1411001918,"description":" &lt;a href=&quot;https://rarbg.com&quot; rel=&quot;nofollow&quot; target=&quot;_NEW&quot;&gt;https://rarbg.com&lt;/a&gt;\n\nDoghouseDigital.com_12.11.29.Her.First.MILF.5.Scene.5.XXX.IMAGESET-GUSH\n","torrent":{"xt":"urn:btih:84189aedc04a454965bb6c1ec8242d14cf559039","amp;dn":"DoghouseDigital.12.11.29.Her.First.MILF.5.Scene.5.XXX.IMAGESET-G","amp;tr":["udp%3A%2F%2Ftracker.openbittorrent.com%3A80","udp%3A%2F%2Fopen.demonii.com%3A1337","udp%3A%2F%2Ftracker.coppersurfer.tk%3A6969","udp%3A%2F%2Fexodus.desync.com%3A6969"],"infoHash":"84189aedc04a454965bb6c1ec8242d14cf559039","infoHashBuffer":{"type":"Buffer","data":[132,24,154,237,192,74,69,73,101,187,108,30,200,36,45,20,207,85,144,57]},"announce":[],"urlList":[]}}