{"title":"Megazone.23.Part.III.Part.II.1989.DVDRip.x264-WaLMaRT","uid":11795238,"size":498855079,"categoryP":"video","categoryS":"movies","magnet":"?xt=urn:btih:99d895dc34e95cabaacead35199f67f31ad20044&amp;dn=Megazone.23.Part.III.Part.II.1989.DVDRip.x264-WaLMaRT&amp;tr=udp%3A%2F%2Ftracker.openbittorrent.com%3A80&amp;tr=udp%3A%2F%2Fopen.demonii.com%3A1337&amp;tr=udp%3A%2F%2Ftracker.coppersurfer.tk%3A6969&amp;tr=udp%3A%2F%2Fexodus.desync.com%3A6969","seeders":0,"leechers":1,"uploader":"TvTeam","files":7,"time":1428130199,"description":" &lt;a href=&quot;https://www.torrenting.com&quot; rel=&quot;nofollow&quot; target=&quot;_NEW&quot;&gt;https://www.torrenting.com&lt;/a&gt;\n\nSign up is OPEN - for the time being. Come and have fun","torrent":{"xt":"urn:btih:99d895dc34e95cabaacead35199f67f31ad20044","amp;dn":"Megazone.23.Part.III.Part.II.1989.DVDRip.x264-WaLMaRT","amp;tr":["udp%3A%2F%2Ftracker.openbittorrent.com%3A80","udp%3A%2F%2Fopen.demonii.com%3A1337","udp%3A%2F%2Ftracker.coppersurfer.tk%3A6969","udp%3A%2F%2Fexodus.desync.com%3A6969"],"infoHash":"99d895dc34e95cabaacead35199f67f31ad20044","infoHashBuffer":{"type":"Buffer","data":[153,216,149,220,52,233,92,171,170,206,173,53,25,159,103,243,26,210,0,68]},"announce":[],"urlList":[]}}