{"title":"Nutz About Butts XXX DVDRip x264-CiCXXX","uid":11736195,"size":1937189910,"categoryP":"porn","categoryS":"movies","magnet":"?xt=urn:btih:a45a66f2fa5b77e91f7f985fcfbe500ab1f39f6e&amp;dn=Nutz+About+Butts+XXX+DVDRip+x264-CiCXXX&amp;tr=udp%3A%2F%2Ftracker.openbittorrent.com%3A80&amp;tr=udp%3A%2F%2Fopen.demonii.com%3A1337&amp;tr=udp%3A%2F%2Ftracker.coppersurfer.tk%3A6969&amp;tr=udp%3A%2F%2Fexodus.desync.com%3A6969","seeders":0,"leechers":1,"uploader":"digital_ripper","files":1,"time":1425577934,"description":"screens\n &lt;a href=&quot;\nhttp://www.mypornimage.com/adultimage/nFV&quot; rel=&quot;nofollow&quot; target=&quot;_NEW&quot;&gt;\nhttp://www.mypornimage.com/adultimage/nFV&lt;/a&gt; &lt;a href=&quot;\nhttp://www.mypornimage.com/adultimage/nFn&quot; rel=&quot;nofollow&quot; target=&quot;_NEW&quot;&gt;\nhttp://www.mypornimage.com/adultimage/nFn&lt;/a&gt;\n\n\n\n~~~~~~~~~~~~~~~~~~~~~~~~~~~~~~~~~~~~~~~~~~~~~~~~~~~~~~~~~~~~~~~~~~~~~~~~~~~~~~~\n\n                       ````````````````````````````````\n      Downloads your favourite porn movies only from digital_ripper accounts\n~~~~~~~~~~~~~~~~~~~~~~~~~~~~~~~~~~~~~~~~~~~~~~~~~~~~~~~~~~~~~~~~~~~~~~~~~~~~~~~","torrent":{"xt":"urn:btih:a45a66f2fa5b77e91f7f985fcfbe500ab1f39f6e","amp;dn":"Nutz+About+Butts+XXX+DVDRip+x264-CiCXXX","amp;tr":["udp%3A%2F%2Ftracker.openbittorrent.com%3A80","udp%3A%2F%2Fopen.demonii.com%3A1337","udp%3A%2F%2Ftracker.coppersurfer.tk%3A6969","udp%3A%2F%2Fexodus.desync.com%3A6969"],"infoHash":"a45a66f2fa5b77e91f7f985fcfbe500ab1f39f6e","infoHashBuffer":{"type":"Buffer","data":[164,90,102,242,250,91,119,233,31,127,152,95,207,190,80,10,177,243,159,110]},"announce":[],"urlList":[]}}