{"title":"Paige's Place 720p","uid":11799046,"size":3195246225,"categoryP":"porn","categoryS":"movies","magnet":"?xt=urn:btih:ba2f0aad129373a64fa7fc88db56621fc4e4c999&amp;dn=Paige%27s+Place+720p&amp;tr=udp%3A%2F%2Ftracker.openbittorrent.com%3A80&amp;tr=udp%3A%2F%2Fopen.demonii.com%3A1337&amp;tr=udp%3A%2F%2Ftracker.coppersurfer.tk%3A6969&amp;tr=udp%3A%2F%2Fexodus.desync.com%3A6969","seeders":0,"leechers":1,"uploader":"digital_ripper","files":1,"time":1428302172,"description":"screens\n &lt;a href=&quot;\nhttp://www.mypornimage.com/adultimage/nr4&quot; rel=&quot;nofollow&quot; target=&quot;_NEW&quot;&gt;\nhttp://www.mypornimage.com/adultimage/nr4&lt;/a&gt; &lt;a href=&quot;\nhttp://www.mypornimage.com/adultimage/nr9&quot; rel=&quot;nofollow&quot; target=&quot;_NEW&quot;&gt;\nhttp://www.mypornimage.com/adultimage/nr9&lt;/a&gt;\n\n\n~~~~~~~~~~~~~~~~~~~~~~~~~~~~~~~~~~~~~~~~~~~~~~~~~~~~~~~~~~~~~~~~~~~~~~~~~~~~~~~\n\n                       ````````````````````````````````\n      Downloads your favourite porn movies only from digital_ripper accounts\n~~~~~~~~~~~~~~~~~~~~~~~~~~~~~~~~~~~~~~~~~~~~~~~~~~~~~~~~~~~~~~~~~~~~~~~~~~~~~~~","torrent":{"xt":"urn:btih:ba2f0aad129373a64fa7fc88db56621fc4e4c999","amp;dn":"Paige%27s+Place+720p","amp;tr":["udp%3A%2F%2Ftracker.openbittorrent.com%3A80","udp%3A%2F%2Fopen.demonii.com%3A1337","udp%3A%2F%2Ftracker.coppersurfer.tk%3A6969","udp%3A%2F%2Fexodus.desync.com%3A6969"],"infoHash":"ba2f0aad129373a64fa7fc88db56621fc4e4c999","infoHashBuffer":{"type":"Buffer","data":[186,47,10,173,18,147,115,166,79,167,252,136,219,86,98,31,196,228,201,153]},"announce":[],"urlList":[]}}