{"title":"Emily from Naughtymidwestgirls [.wmv]","uid":11806214,"size":522619924,"categoryP":"porn","categoryS":"other","magnet":"?xt=urn:btih:c6e06b500434e3ff74a873872131ccb14b0b72ca&amp;dn=Emily+from+Naughtymidwestgirls+%5B.wmv%5D+&amp;tr=udp%3A%2F%2Ftracker.openbittorrent.com%3A80&amp;tr=udp%3A%2F%2Fopen.demonii.com%3A1337&amp;tr=udp%3A%2F%2Ftracker.coppersurfer.tk%3A6969&amp;tr=udp%3A%2F%2Fexodus.desync.com%3A6969","seeders":0,"leechers":7,"uploader":"bittuboss","files":3,"time":1428598586,"description":"ScReenS...\n &lt;a href=&quot;\nhttp://imgextra.biz/img-552693a20283d.html&quot; rel=&quot;nofollow&quot; target=&quot;_NEW&quot;&gt;\nhttp://imgextra.biz/img-552693a20283d.html&lt;/a&gt;\n &lt;a href=&quot;\nhttp://imgextra.biz/img-552693a23dbb3.html&quot; rel=&quot;nofollow&quot; target=&quot;_NEW&quot;&gt;\nhttp://imgextra.biz/img-552693a23dbb3.html&lt;/a&gt;","torrent":{"xt":"urn:btih:c6e06b500434e3ff74a873872131ccb14b0b72ca","amp;dn":"Emily+from+Naughtymidwestgirls+%5B.wmv%5D+","amp;tr":["udp%3A%2F%2Ftracker.openbittorrent.com%3A80","udp%3A%2F%2Fopen.demonii.com%3A1337","udp%3A%2F%2Ftracker.coppersurfer.tk%3A6969","udp%3A%2F%2Fexodus.desync.com%3A6969"],"infoHash":"c6e06b500434e3ff74a873872131ccb14b0b72ca","infoHashBuffer":{"type":"Buffer","data":[198,224,107,80,4,52,227,255,116,168,115,135,33,49,204,177,75,11,114,202]},"announce":[],"urlList":[]}}