{"title":"UK Hottest MILFs 2014 WEB-DL torrent","uid":11021069,"size":2307536662,"categoryP":"porn","categoryS":"other","magnet":"?xt=urn:btih:c6ed382e483d6c324d973a5050c965ff51ffb41e&amp;dn=UK+Hottest+MILFs+2014+WEB-DL+torrent&amp;tr=udp%3A%2F%2Ftracker.openbittorrent.com%3A80&amp;tr=udp%3A%2F%2Fopen.demonii.com%3A1337&amp;tr=udp%3A%2F%2Ftracker.coppersurfer.tk%3A6969&amp;tr=udp%3A%2F%2Fexodus.desync.com%3A6969","seeders":0,"leechers":0,"uploader":"TomcatX","files":1,"time":1410572072,"description":"UK Hottest MILFs 2014 WEB-DL torrent\n\n\n......::::SCREENSHOTS::::......  &lt;a href=&quot;\nhttp://www.imgextra.biz/viewer.php?file=baixtgj5by9cbhy4ky51.jpg&quot; rel=&quot;nofollow&quot; target=&quot;_NEW&quot;&gt;\nhttp://www.imgextra.biz/viewer.php?file=baixtgj5by9cbhy4ky51.jpg&lt;/a&gt; &lt;a href=&quot;\nhttp://www.imgextra.biz/viewer.php?file=4bo6m3znptimk2p29v2.jpg&quot; rel=&quot;nofollow&quot; target=&quot;_NEW&quot;&gt;\nhttp://www.imgextra.biz/viewer.php?file=4bo6m3znptimk2p29v2.jpg&lt;/a&gt;\n\nFor more Click Here ::: &lt;a href=&quot;\nhttp://thepiratebay.org.in/user/TomcatX/&quot; rel=&quot;nofollow&quot; target=&quot;_NEW&quot;&gt;\nhttp://thepiratebay.org.in/user/TomcatX/&lt;/a&gt;\n\nHI SPEED DOWNLOAD","torrent":{"xt":"urn:btih:c6ed382e483d6c324d973a5050c965ff51ffb41e","amp;dn":"UK+Hottest+MILFs+2014+WEB-DL+torrent","amp;tr":["udp%3A%2F%2Ftracker.openbittorrent.com%3A80","udp%3A%2F%2Fopen.demonii.com%3A1337","udp%3A%2F%2Ftracker.coppersurfer.tk%3A6969","udp%3A%2F%2Fexodus.desync.com%3A6969"],"infoHash":"c6ed382e483d6c324d973a5050c965ff51ffb41e","infoHashBuffer":{"type":"Buffer","data":[198,237,56,46,72,61,108,50,77,151,58,80,80,201,101,255,81,255,180,30]},"announce":[],"urlList":[]}}