{"title":"[Honky Tonk Teens] Nikki Benz Rides Hard DVDRip [.avi]","uid":10895417,"size":734197760,"categoryP":"porn","categoryS":"movies","magnet":"?xt=urn:btih:cf38cd9ce0a905200b9fa23b56fbce98a47a123b&amp;dn=%5BHonky+Tonk+Teens%5D+Nikki+Benz+Rides+Hard+DVDRip+%5B.avi%5D&amp;tr=udp%3A%2F%2Ftracker.openbittorrent.com%3A80&amp;tr=udp%3A%2F%2Fopen.demonii.com%3A1337&amp;tr=udp%3A%2F%2Ftracker.coppersurfer.tk%3A6969&amp;tr=udp%3A%2F%2Fexodus.desync.com%3A6969","seeders":0,"leechers":1,"uploader":"-MosT-WanteD-","files":1,"time":1409155859,"description":"[Honky Tonk Teens] Nikki Benz Rides Hard DVDRip [.avi]\n\nWell Worth The Reward...Nikki Benz Rides Real Hard!!! Check out Rio Grande!! There's nothin' like a country girl to honky on your tonky and the girls from the deep south got it goin' on down south of the naval, if you know what I mean? Check it out and don't forget to honk your tonk along the way!!\n\nCast:\nNikki Benz, Katie Gold, Kathleen Cruz, Daphine, Melissa.\n\n============================================\n &lt;a href=&quot;\nhttp://imgruby.com/?v=631265&quot; rel=&quot;nofollow&quot; target=&quot;_NEW&quot;&gt;\nhttp://imgruby.com/?v=631265&lt;/a&gt;\n &lt;a href=&quot;\nhttp://imgruby.com/?v=294116&quot; rel=&quot;nofollow&quot; target=&quot;_NEW&quot;&gt;\nhttp://imgruby.com/?v=294116&lt;/a&gt;","torrent":{"xt":"urn:btih:cf38cd9ce0a905200b9fa23b56fbce98a47a123b","amp;dn":"%5BHonky+Tonk+Teens%5D+Nikki+Benz+Rides+Hard+DVDRip+%5B.avi%5D","amp;tr":["udp%3A%2F%2Ftracker.openbittorrent.com%3A80","udp%3A%2F%2Fopen.demonii.com%3A1337","udp%3A%2F%2Ftracker.coppersurfer.tk%3A6969","udp%3A%2F%2Fexodus.desync.com%3A6969"],"infoHash":"cf38cd9ce0a905200b9fa23b56fbce98a47a123b","infoHashBuffer":{"type":"Buffer","data":[207,56,205,156,224,169,5,32,11,159,162,59,86,251,206,152,164,122,18,59]},"announce":[],"urlList":[]}}