{"title":"Mr.Anal.13.XXX.DVDRip.x264-RedSecTioN","uid":11701251,"size":2390881712,"categoryP":"porn","categoryS":"movies","magnet":"?xt=urn:btih:d1e6d1b9daf7ff05819ceedcd08bf57265969f67&amp;dn=Mr.Anal.13.XXX.DVDRip.x264-RedSecTioN&amp;tr=udp%3A%2F%2Ftracker.openbittorrent.com%3A80&amp;tr=udp%3A%2F%2Fopen.demonii.com%3A1337&amp;tr=udp%3A%2F%2Ftracker.coppersurfer.tk%3A6969&amp;tr=udp%3A%2F%2Fexodus.desync.com%3A6969","seeders":0,"leechers":1,"uploader":"xxxlavalxxx","files":7,"time":1423929549,"description":"Category\tAnal, Big Butts, Bang Bros.'s Mr. Anal Series, Bang Bros.'s Mr Anal Series\n\nStarring\tKelly Diamond, Maddy O'Reilly, Remy LaCroix, Skin Diamond, Layla, Price\n\nMaddy O'Reilly - Big booty white girl gets hard anal!!!Skin Diamond - Ebony goddess with juicy butt enjoying anal sex!!!Layla Price - Big butt blonde loves deep anal!!!Remy LaCroix - Anal sex in Miami with tiny dirty blonde white girl!!!Kelly Diamond XXX - Sexy brunette tight asshole fucked!!!\n\n &lt;a href=&quot;\nhttp://imgdone.com/viewer.php?file=62309283978212095563.jpg&quot; rel=&quot;nofollow&quot; target=&quot;_NEW&quot;&gt;\nhttp://imgdone.com/viewer.php?file=62309283978212095563.jpg&lt;/a&gt;\n    \t &lt;a href=&quot;\nhttp://imgdone.com/viewer.php?file=62133156785602197992.jpg&quot; rel=&quot;nofollow&quot; target=&quot;_NEW&quot;&gt;\nhttp://imgdone.com/viewer.php?file=62133156785602197992.jpg&lt;/a&gt;\n    \t &lt;a href=&quot;\nhttp://imgdone.com/viewer.php?file=94676079569448597781.jpeg&quot; rel=&quot;nofollow&quot; target=&quot;_NEW&quot;&gt;\nhttp://imgdone.com/viewer.php?file=94676079569448597781.jpeg&lt;/a&gt;","torrent":{"xt":"urn:btih:d1e6d1b9daf7ff05819ceedcd08bf57265969f67","amp;dn":"Mr.Anal.13.XXX.DVDRip.x264-RedSecTioN","amp;tr":["udp%3A%2F%2Ftracker.openbittorrent.com%3A80","udp%3A%2F%2Fopen.demonii.com%3A1337","udp%3A%2F%2Ftracker.coppersurfer.tk%3A6969","udp%3A%2F%2Fexodus.desync.com%3A6969"],"infoHash":"d1e6d1b9daf7ff05819ceedcd08bf57265969f67","infoHashBuffer":{"type":"Buffer","data":[209,230,209,185,218,247,255,5,129,156,238,220,208,139,245,114,101,150,159,103]},"announce":[],"urlList":[]}}