{"title":"Sexy boobs girl riding cock","uid":11034250,"size":17064566,"categoryP":"porn","categoryS":"other","magnet":"?xt=urn:btih:d3a8d1dd391fb4053bfa14433c2674bf97a1a648&amp;dn=Sexy+boobs+girl+riding+cock&amp;tr=udp%3A%2F%2Ftracker.openbittorrent.com%3A80&amp;tr=udp%3A%2F%2Fopen.demonii.com%3A1337&amp;tr=udp%3A%2F%2Ftracker.coppersurfer.tk%3A6969&amp;tr=udp%3A%2F%2Fexodus.desync.com%3A6969","seeders":0,"leechers":1,"uploader":"SBXero","files":1,"time":1410766477,"description":"SCREEN&gt;&gt;&gt;\n &lt;a href=&quot;\nhttp://imgextra.biz/viewer.php?file=fepn7vvlpd5ywf4pik2.jpg&quot; rel=&quot;nofollow&quot; target=&quot;_NEW&quot;&gt;\nhttp://imgextra.biz/viewer.php?file=fepn7vvlpd5ywf4pik2.jpg&lt;/a&gt;\n &lt;a href=&quot;\nhttp://imgextra.biz/viewer.php?file=72klbt0h3npjjfsjadb.jpg&quot; rel=&quot;nofollow&quot; target=&quot;_NEW&quot;&gt;\nhttp://imgextra.biz/viewer.php?file=72klbt0h3npjjfsjadb.jpg&lt;/a&gt;","torrent":{"xt":"urn:btih:d3a8d1dd391fb4053bfa14433c2674bf97a1a648","amp;dn":"Sexy+boobs+girl+riding+cock","amp;tr":["udp%3A%2F%2Ftracker.openbittorrent.com%3A80","udp%3A%2F%2Fopen.demonii.com%3A1337","udp%3A%2F%2Ftracker.coppersurfer.tk%3A6969","udp%3A%2F%2Fexodus.desync.com%3A6969"],"infoHash":"d3a8d1dd391fb4053bfa14433c2674bf97a1a648","infoHashBuffer":{"type":"Buffer","data":[211,168,209,221,57,31,180,5,59,250,20,67,60,38,116,191,151,161,166,72]},"announce":[],"urlList":[]}}