{"title":"PBS Operation Maneater 2of3 Polar Bear 720p x264 AAC HDTV ","uid":11058191,"size":1039387529,"categoryP":"video","categoryS":"hd___tv_shows","magnet":"?xt=urn:btih:d9a62e58e9adfa733df0f164856e81664125310d&amp;dn=PBS+Operation+Maneater+2of3+Polar+Bear+720p+x264+AAC+HDTV+&amp;tr=udp%3A%2F%2Ftracker.openbittorrent.com%3A80&amp;tr=udp%3A%2F%2Fopen.demonii.com%3A1337&amp;tr=udp%3A%2F%2Ftracker.coppersurfer.tk%3A6969&amp;tr=udp%3A%2F%2Fexodus.desync.com%3A6969","seeders":0,"leechers":0,"uploader":"MVGroup","files":-1,"time":1411140823,"description":"Operation Maneater\n\nNature Documentary hosted by Mark Evans, published by PBS in 2014 - English narration\n\n\nInformation\n------------------------------\n\nIn OPERATION MANEATER, veterinarian Mark Evans uses technology to tackle three of nature's deadliest giants: the Nile Crocodile, the Polar Bear, and the Great White Shark. When these animals attack humans, both sides lose out. Mark Evans is on a personal mission to find ways to break the circle of violence. Follow him as he tries out ingenious high-tech solutions to the most hostile wildlife conflicts on Earth.\n\n\n1)  Great White Shark \nThe Southwest Australian coast near Perth is the shark attack capital of the world. Last summer saw a record number of five fatal shark attacks. Australians love to swim, surf and dive, but many are now scared to enter the water. The situation has become so desperate that the authorities have implemented radical measures - sharks found near beachgoers can now be hunted and killed.\n\n2)  Polar Bear \nMark Evans travels to the shores of Canada's Hudson Bay. Every year bears congregate along this coast as they wait for the sea ice to harden so they can they head north and feast on seals. But bold bears are venturing into the towns of Churchill and Arviat and are terrorizing local residents. Three people have been viciously attacked in recent months and bears are regularly shot dead in self-defence.\n\n3)  Crocodile \nMark Evans travels to the reputed croc attack capital of the world: Namibia's Chobe River. Crocodiles eat more humans than any other predator and Africa's Nile crocodiles are notoriously aggressive. Namibian conservation efforts to save Nile Crocodiles have been more than successful. Crocodiles here are growing in number, attacks are on the rise and locals are killing crocs in retaliation.\n\nScreenshots\n------------------------------ &lt;a href=&quot;\nhttp://image.bayimg.com/a073c7a0625bec9eb5383a98082fde7446e46575.jpg&quot; rel=&quot;nofollow&quot; target=&quot;_NEW&quot;&gt;\nhttp://image.bayimg.com/a073c7a0625bec9eb5383a98082fde7446e46575.jpg&lt;/a&gt; &lt;a href=&quot;\nhttp://image.bayimg.com/68e4fc87b6e840a124516f9e954824723277ff70.jpg&quot; rel=&quot;nofollow&quot; target=&quot;_NEW&quot;&gt;\nhttp://image.bayimg.com/68e4fc87b6e840a124516f9e954824723277ff70.jpg&lt;/a&gt; &lt;a href=&quot;\nhttp://image.bayimg.com/5248e26f2990f3ec9a55139d1e34b19d2f48c0f1.jpg&quot; rel=&quot;nofollow&quot; target=&quot;_NEW&quot;&gt;\nhttp://image.bayimg.com/5248e26f2990f3ec9a55139d1e34b19d2f48c0f1.jpg&lt;/a&gt; &lt;a href=&quot;\nhttp://image.bayimg.com/1c0ccacb7ca09c78ae40197c7480563a0893fef1.jpg&quot; rel=&quot;nofollow&quot; target=&quot;_NEW&quot;&gt;\nhttp://image.bayimg.com/1c0ccacb7ca09c78ae40197c7480563a0893fef1.jpg&lt;/a&gt; &lt;a href=&quot;\nhttp://image.bayimg.com/0bfa4782870256f9d94a41972f451a79077329ce.jpg&quot; rel=&quot;nofollow&quot; target=&quot;_NEW&quot;&gt;\nhttp://image.bayimg.com/0bfa4782870256f9d94a41972f451a79077329ce.jpg&lt;/a&gt; &lt;a href=&quot;\nhttp://image.bayimg.com/264f7c81a81e5403fbeb371244c02adb6f1f1536.jpg&quot; rel=&quot;nofollow&quot; target=&quot;_NEW&quot;&gt;\nhttp://image.bayimg.com/264f7c81a81e5403fbeb371244c02adb6f1f1536.jpg&lt;/a&gt; &lt;a href=&quot;\nhttp://image.bayimg.com/fbb3d76936e36a0b79065d73c5476d9421c2dffe.jpg&quot; rel=&quot;nofollow&quot; target=&quot;_NEW&quot;&gt;\nhttp://image.bayimg.com/fbb3d76936e36a0b79065d73c5476d9421c2dffe.jpg&lt;/a&gt; &lt;a href=&quot;\nhttp://image.bayimg.com/3b400cd3a2bb53b73645170ec2baaf091b744b69.jpg&quot; rel=&quot;nofollow&quot; target=&quot;_NEW&quot;&gt;\nhttp://image.bayimg.com/3b400cd3a2bb53b73645170ec2baaf091b744b69.jpg&lt;/a&gt; &lt;a href=&quot;\nhttp://image.bayimg.com/ecf6ed1e618bdd14dbed4a81a4a9ce3f8af12732.jpg&quot; rel=&quot;nofollow&quot; target=&quot;_NEW&quot;&gt;\nhttp://image.bayimg.com/ecf6ed1e618bdd14dbed4a81a4a9ce3f8af12732.jpg&lt;/a&gt; \n\nTechnical Specs\n------------------------------\n\n\n * Video Codec: x264 CABAC &lt;a class=&quot;__cf_email__&quot; href=&quot;/cdn-cgi/l/email-protection&quot; data-cfemail=&quot;5f173638371f136b716e&quot;&gt;[email&amp;#160;protected]&lt;/a&gt;&lt;script data-cfhash='f9e31' type=&quot;text/javascript&quot;&gt;\n/* &lt;![CDATA[ */!function(){try{var t=&quot;currentScript&quot;in document?document.currentScript:function(){for(var t=document.getElementsByTagName(&quot;script&quot;),e=t.length;e--;)if(t[e].getAttribute(&quot;data-cfhash&quot;))return t[e]}();if(t&amp;&amp;t.previousSibling){var e,r,n,i,c=t.previousSibling,a=c.getAttribute(&quot;data-cfemail&quot;);if(a){for(e=&quot;&quot;,r=parseInt(a.substr(0,2),16),n=2;a.length-n;n+=2)i=parseInt(a.substr(n,2),16)^r,e+=String.fromCharCode(i);e=document.createTextNode(e),c.parentNode.replaceChild(e,c)}t.parentNode.removeChild(t);}}catch(u){}}()/* ]]&gt; */&lt;/script&gt;\n * Video Bitrate: ~2900 Kbps (CRF 21)\n * Video Resolution: 1280x720\n * Video Aspect Ratio: 16:9\n * Framerate: 25 fps\n * Audio Codec: AAC-LC (Nero)\n * Audio Quality: 0.50 48KHz (~150 Kbps)\n * Audio Channels: 2\n * Run-Time: ~55mn (2h 45mn Total)\n * Number of Parts: 3\n * Part Size: ~1.16 GiB (each)\n * Container: MP4\n * Released: 2014\n * Source: HDTV\n * Capper: KarMa\n * Subtitles: English - Merged in the MP4\n\n\n\nLinks\n------------------------------\n\n1)  Further Information &lt;a href=&quot;\nhttp://www.pbs.org/program/operation-maneater/&quot; rel=&quot;nofollow&quot; target=&quot;_NEW&quot;&gt;\nhttp://www.pbs.org/program/operation-maneater/&lt;/a&gt;\n\n2)  Related Documentaries &lt;a href=&quot;\nhttp://docuwiki.net/?title=Why%20Sharks%20Attack%20-%20Secrets%20of%20the%20Great%20White&quot; rel=&quot;nofollow&quot; target=&quot;_NEW&quot;&gt;\nhttp://docuwiki.net/?title=Why%20Sharks%20Attack%20-%20Secrets%20of%20the%20Great%20White&lt;/a&gt; &lt;a href=&quot;\nhttp://docuwiki.net/?title=Surviving%20Sharks&quot; rel=&quot;nofollow&quot; target=&quot;_NEW&quot;&gt;\nhttp://docuwiki.net/?title=Surviving%20Sharks&lt;/a&gt; &lt;a href=&quot;\nhttp://docuwiki.net/?title=Polar%20Bear&quot; rel=&quot;nofollow&quot; target=&quot;_NEW&quot;&gt;\nhttp://docuwiki.net/?title=Polar%20Bear&lt;/a&gt; &lt;a href=&quot;\nhttp://docuwiki.net/?title=Polar%20Bear%3A%20Spy%20on%20the%20Ice&quot; rel=&quot;nofollow&quot; target=&quot;_NEW&quot;&gt;\nhttp://docuwiki.net/?title=Polar%20Bear%3A%20Spy%20on%20the%20Ice&lt;/a&gt; &lt;a href=&quot;\nhttp://docuwiki.net/?title=Crocodile%20%28Ch4%29&quot; rel=&quot;nofollow&quot; target=&quot;_NEW&quot;&gt;\nhttp://docuwiki.net/?title=Crocodile%20%28Ch4%29&lt;/a&gt; &lt;a href=&quot;\nhttp://docuwiki.net/?title=Crocpocalypse&quot; rel=&quot;nofollow&quot; target=&quot;_NEW&quot;&gt;\nhttp://docuwiki.net/?title=Crocpocalypse&lt;/a&gt;\n\n3)  ed2k Links \n\n\n\n\n\n\nAdded by &lt;a href=&quot;\nhttp://docuwiki.net/?title=User%3AKarmax264&quot; rel=&quot;nofollow&quot; target=&quot;_NEW&quot;&gt;\nhttp://docuwiki.net/?title=User%3AKarmax264&lt;/a&gt;\n\nSource: &lt;a href=&quot;\nhttp://docuwiki.net/index.php?title=Operation_Maneater&quot; rel=&quot;nofollow&quot; target=&quot;_NEW&quot;&gt;\nhttp://docuwiki.net/index.php?title=Operation_Maneater&lt;/a&gt;\n","torrent":{"xt":"urn:btih:d9a62e58e9adfa733df0f164856e81664125310d","amp;dn":"PBS+Operation+Maneater+2of3+Polar+Bear+720p+x264+AAC+HDTV+","amp;tr":["udp%3A%2F%2Ftracker.openbittorrent.com%3A80","udp%3A%2F%2Fopen.demonii.com%3A1337","udp%3A%2F%2Ftracker.coppersurfer.tk%3A6969","udp%3A%2F%2Fexodus.desync.com%3A6969"],"infoHash":"d9a62e58e9adfa733df0f164856e81664125310d","infoHashBuffer":{"type":"Buffer","data":[217,166,46,88,233,173,250,115,61,240,241,100,133,110,129,102,65,37,49,13]},"announce":[],"urlList":[]}}