{"title":"David.Letterman.2014.12.11.Chris.Rock.720p.WEBCap.x264.BYTE","uid":11674966,"size":1078828920,"categoryP":"video","categoryS":"hd___tv_shows","magnet":"?xt=urn:btih:df3b2056cd6d09ce93a6722d573765ff78c853ca&amp;dn=David.Letterman.2014.12.11.Chris.Rock.720p.WEBCap.x264.BYTE&amp;tr=udp%3A%2F%2Ftracker.openbittorrent.com%3A80&amp;tr=udp%3A%2F%2Fopen.demonii.com%3A1337&amp;tr=udp%3A%2F%2Ftracker.coppersurfer.tk%3A6969&amp;tr=udp%3A%2F%2Fexodus.desync.com%3A6969","seeders":0,"leechers":1,"uploader":"LateByte2","files":1,"time":1422817805,"description":"David.Letterman.2014.12.11.Chris.Rock.720p.WEBCap.x264.BYTE\n\nThanks to TPB\n\nPlease seed so I can share more. Thanks!","torrent":{"xt":"urn:btih:df3b2056cd6d09ce93a6722d573765ff78c853ca","amp;dn":"David.Letterman.2014.12.11.Chris.Rock.720p.WEBCap.x264.BYTE","amp;tr":["udp%3A%2F%2Ftracker.openbittorrent.com%3A80","udp%3A%2F%2Fopen.demonii.com%3A1337","udp%3A%2F%2Ftracker.coppersurfer.tk%3A6969","udp%3A%2F%2Fexodus.desync.com%3A6969"],"infoHash":"df3b2056cd6d09ce93a6722d573765ff78c853ca","infoHashBuffer":{"type":"Buffer","data":[223,59,32,86,205,109,9,206,147,166,114,45,87,55,101,255,120,200,83,202]},"announce":[],"urlList":[]}}