{"title":"GBG-003 amateur JAV CENSORED","uid":11041675,"size":1638821531,"categoryP":"porn","categoryS":"movie_clips","magnet":"?xt=urn:btih:e900cf6aef44c4d4b0bc7c627b85bfe4b824457e&amp;dn=GBG-003+amateur+JAV+CENSORED&amp;tr=udp%3A%2F%2Ftracker.openbittorrent.com%3A80&amp;tr=udp%3A%2F%2Fopen.demonii.com%3A1337&amp;tr=udp%3A%2F%2Ftracker.coppersurfer.tk%3A6969&amp;tr=udp%3A%2F%2Fexodus.desync.com%3A6969","seeders":0,"leechers":1,"uploader":"3xplanet","files":1,"time":1410826885,"description":"GBG-003 amateur JAV CENSORED\nCover &lt;a href=&quot;\nhttp://www.3xplanet.com/view/55843.html&quot; rel=&quot;nofollow&quot; target=&quot;_NEW&quot;&gt;\nhttp://www.3xplanet.com/view/55843.html&lt;/a&gt;\nScreenshot &lt;a href=&quot;\nhttp://www.3xplanet.com/view/55895.html&quot; rel=&quot;nofollow&quot; target=&quot;_NEW&quot;&gt;\nhttp://www.3xplanet.com/view/55895.html&lt;/a&gt;\nTitle: \nStarring: amateur\nStudio:  HERO\n\nTag: JAV, CENSORED, HERO, housewife, cum inside, Creampie, Big tits\n\n","torrent":{"xt":"urn:btih:e900cf6aef44c4d4b0bc7c627b85bfe4b824457e","amp;dn":"GBG-003+amateur+JAV+CENSORED","amp;tr":["udp%3A%2F%2Ftracker.openbittorrent.com%3A80","udp%3A%2F%2Fopen.demonii.com%3A1337","udp%3A%2F%2Ftracker.coppersurfer.tk%3A6969","udp%3A%2F%2Fexodus.desync.com%3A6969"],"infoHash":"e900cf6aef44c4d4b0bc7c627b85bfe4b824457e","infoHashBuffer":{"type":"Buffer","data":[233,0,207,106,239,68,196,212,176,188,124,98,123,133,191,228,184,36,69,126]},"announce":[],"urlList":[]}}