{"title":"BEX BRAZZERS EXXTRA - Lezley Zen  - Sexy Silhouette - NEW 12 AUG","uid":10746612,"size":275088294,"categoryP":"porn","categoryS":"movie_clips","magnet":"?xt=urn:btih:f019cbf69ae427bef5eabf50bcd92481c1c1ca06&amp;dn=BEX+BRAZZERS+EXXTRA+-+Lezley+Zen++-+Sexy+Silhouette+-+NEW+12+AUG&amp;tr=udp%3A%2F%2Ftracker.openbittorrent.com%3A80&amp;tr=udp%3A%2F%2Fopen.demonii.com%3A1337&amp;tr=udp%3A%2F%2Ftracker.coppersurfer.tk%3A6969&amp;tr=udp%3A%2F%2Fexodus.desync.com%3A6969","seeders":0,"leechers":1,"uploader":"manam69","files":1,"time":1407824495,"description":"BEX BRAZZERS EXXTRA - Lezley Zen  - Sexy Silhouette - NEW 12 AUGUST 2014 NEW\n\n\nLezley Zen is a master of the fine art of fellatio, so we got the raven-haired beauty to do a nice POV blowjob for all you horny pervs out there. First, she teases the camera with a sexy, sensual, and slow strip tease, slipping out of her panties and dropping to her knees to get at that cock. She talks dirty as she face fucks that big dick, taking it deep in her throat and jerking it off until she gets a nice big facial cumshot!\n\n\n\n\n &lt;a href=&quot;\nhttp://s20.postimg.org/9pcrjraf1/image.jpg&quot; rel=&quot;nofollow&quot; target=&quot;_NEW&quot;&gt;\nhttp://s20.postimg.org/9pcrjraf1/image.jpg&lt;/a&gt;\n &lt;a href=&quot;\nhttp://s20.postimg.org/hw4rbc0hp/bex_lezley_zen.jpg&quot; rel=&quot;nofollow&quot; target=&quot;_NEW&quot;&gt;\nhttp://s20.postimg.org/hw4rbc0hp/bex_lezley_zen.jpg&lt;/a&gt;","torrent":{"xt":"urn:btih:f019cbf69ae427bef5eabf50bcd92481c1c1ca06","amp;dn":"BEX+BRAZZERS+EXXTRA+-+Lezley+Zen++-+Sexy+Silhouette+-+NEW+12+AUG","amp;tr":["udp%3A%2F%2Ftracker.openbittorrent.com%3A80","udp%3A%2F%2Fopen.demonii.com%3A1337","udp%3A%2F%2Ftracker.coppersurfer.tk%3A6969","udp%3A%2F%2Fexodus.desync.com%3A6969"],"infoHash":"f019cbf69ae427bef5eabf50bcd92481c1c1ca06","infoHashBuffer":{"type":"Buffer","data":[240,25,203,246,154,228,39,190,245,234,191,80,188,217,36,129,193,193,202,6]},"announce":[],"urlList":[]}}