{"title":"SexAsian18.14.08.18.Selfie.Sex.XXX.DiVX-oRo","uid":11011704,"size":1612472023,"categoryP":"porn","categoryS":"other","magnet":"?xt=urn:btih:fcdb7808f72ab58b0971ed0eee9d9618c2533d9a&amp;dn=SexAsian18.14.08.18.Selfie.Sex.XXX.DiVX-oRo&amp;tr=udp%3A%2F%2Ftracker.openbittorrent.com%3A80&amp;tr=udp%3A%2F%2Fopen.demonii.com%3A1337&amp;tr=udp%3A%2F%2Ftracker.coppersurfer.tk%3A6969&amp;tr=udp%3A%2F%2Fexodus.desync.com%3A6969","seeders":0,"leechers":1,"uploader":"DrarbgXXX","files":3,"time":1410369822,"description":" &lt;a href=&quot;https://rarbg.com&quot; rel=&quot;nofollow&quot; target=&quot;_NEW&quot;&gt;https://rarbg.com&lt;/a&gt;\n\nSexAsian18.14.08.18.Selfie.Sex.XXX.DiVX-oRo\n-----------------------------------------\nScreens : &lt;a href=&quot;\nhttp://imagecurl.org/viewer.php?file=18751497309927627459.jpg&quot; rel=&quot;nofollow&quot; target=&quot;_NEW&quot;&gt;\nhttp://imagecurl.org/viewer.php?file=18751497309927627459.jpg&lt;/a&gt;\n\n-----------------------------------------\nAuto Media Info :\nVideo Format........: AVC\nCodec ID............: H264\nLength..............: 2h10mn\nVideo...............: 720x404 ( 29.970fps )\nBitrate.............: 1511Kbps\nAudio Format........: MPEG Audio\nCodec ID............: 55\nCodec ID/Hint.......: MP3\nBit rate mode.......: Constant\nBitrate.............: 128Kbps\nChannel(s)..........: 2 channels\n\n","torrent":{"xt":"urn:btih:fcdb7808f72ab58b0971ed0eee9d9618c2533d9a","amp;dn":"SexAsian18.14.08.18.Selfie.Sex.XXX.DiVX-oRo","amp;tr":["udp%3A%2F%2Ftracker.openbittorrent.com%3A80","udp%3A%2F%2Fopen.demonii.com%3A1337","udp%3A%2F%2Ftracker.coppersurfer.tk%3A6969","udp%3A%2F%2Fexodus.desync.com%3A6969"],"infoHash":"fcdb7808f72ab58b0971ed0eee9d9618c2533d9a","infoHashBuffer":{"type":"Buffer","data":[252,219,120,8,247,42,181,139,9,113,237,14,238,157,150,24,194,83,61,154]},"announce":[],"urlList":[]}}