{"title":"Marvel's.Agent.Carter.S01E07.Snafu.720p.WEB-DL.DD5.1.H.264-Coo7","uid":11711219,"size":1370286318,"categoryP":"video","categoryS":"hd___tv_shows","magnet":"?xt=urn:btih:fd85499db8fa42cb8559f7fee9547a0dbd41b95b&amp;dn=Marvel%27s.Agent.Carter.S01E07.Snafu.720p.WEB-DL.DD5.1.H.264-Coo7&amp;tr=udp%3A%2F%2Ftracker.openbittorrent.com%3A80&amp;tr=udp%3A%2F%2Fopen.demonii.com%3A1337&amp;tr=udp%3A%2F%2Ftracker.coppersurfer.tk%3A6969&amp;tr=udp%3A%2F%2Fexodus.desync.com%3A6969","seeders":0,"leechers":1,"uploader":"sceneline","files":2,"time":1424346512,"description":"\nPlease Seed back to make the speed Faster!!\nand use comment \n ............ NFO","torrent":{"xt":"urn:btih:fd85499db8fa42cb8559f7fee9547a0dbd41b95b","amp;dn":"Marvel%27s.Agent.Carter.S01E07.Snafu.720p.WEB-DL.DD5.1.H.264-Coo7","amp;tr":["udp%3A%2F%2Ftracker.openbittorrent.com%3A80","udp%3A%2F%2Fopen.demonii.com%3A1337","udp%3A%2F%2Ftracker.coppersurfer.tk%3A6969","udp%3A%2F%2Fexodus.desync.com%3A6969"],"infoHash":"fd85499db8fa42cb8559f7fee9547a0dbd41b95b","infoHashBuffer":{"type":"Buffer","data":[253,133,73,157,184,250,66,203,133,89,247,254,233,84,122,13,189,65,185,91]},"announce":[],"urlList":[]}}