{"title":"Stalker.S01E16.HDTV.XviD-iFT","uid":11696504,"size":455321621,"categoryP":"video","categoryS":"tv_shows","magnet":"?xt=urn:btih:ff514aa135bdd2d90c47f1829b0b179c8382735a&amp;dn=Stalker.S01E16.HDTV.XviD-iFT&amp;tr=udp%3A%2F%2Ftracker.openbittorrent.com%3A80&amp;tr=udp%3A%2F%2Fopen.demonii.com%3A1337&amp;tr=udp%3A%2F%2Ftracker.coppersurfer.tk%3A6969&amp;tr=udp%3A%2F%2Fexodus.desync.com%3A6969","seeders":0,"leechers":1,"uploader":"TvTeam","files":3,"time":1423733937,"description":" &lt;a href=&quot;https://www.torrenting.com&quot; rel=&quot;nofollow&quot; target=&quot;_NEW&quot;&gt;https://www.torrenting.com&lt;/a&gt;\n\nSign up is OPEN - for time being. Come and have fun.\n------------------------------------------------------------------------\n\nRELEASE ........: Stalker.S01E16.HDTV.XviD-iFT                                                                                                                       \nRELEASE DATE....: 12/02/2015 \niMDB URL........: http://www.imdb.com/title/tt3560094/\nGENRE...........: Drama | Thriller               \nSOURCE .........: DIMENSION &lt; Thanks &gt;      \nFRAMERATE.......: 23.976 fps\nViDEO BiTRATE...: XviD at 1 289 Kbps                         \nAUDiO ..........: MP3 at 160 Kbps ENGLISH \nRUNTiME.........: 41mn 47s 136ms\nRESOLUTiON......: 640 x 352\nSUBTiTLES.......: N/A\nENCODER.........: Du\nFilE SiZE.......: 434 MiB \n\n@  BECAUSE WE DONT HAVE LIMITS @\n\n\n GREETZ TO ALL P2P","torrent":{"xt":"urn:btih:ff514aa135bdd2d90c47f1829b0b179c8382735a","amp;dn":"Stalker.S01E16.HDTV.XviD-iFT","amp;tr":["udp%3A%2F%2Ftracker.openbittorrent.com%3A80","udp%3A%2F%2Fopen.demonii.com%3A1337","udp%3A%2F%2Ftracker.coppersurfer.tk%3A6969","udp%3A%2F%2Fexodus.desync.com%3A6969"],"infoHash":"ff514aa135bdd2d90c47f1829b0b179c8382735a","infoHashBuffer":{"type":"Buffer","data":[255,81,74,161,53,189,210,217,12,71,241,130,155,11,23,156,131,130,115,90]},"announce":[],"urlList":[]}}